[{"text":"Comparison","collapsed":true,"items":[{"text":"approximatelyTheSame","link":"/../../docs/math/functions/approximatelyTheSame.md"},{"text":"directionAlignedToTangent","link":"/../../docs/math/functions/directionAlignedToTangent.md"},{"text":"sameDirection","link":"/../../docs/math/functions/sameDirection.md"},{"text":"samePoint","link":"/../../docs/math/functions/samePoint.md"}]},{"text":"Angle","collapsed":true,"items":[{"text":"angleSpan","link":"/../../docs/math/functions/angleSpan.md"},{"text":"normalizeAngleZero2TwoPI","link":"/../../docs/math/functions/normalizeAngleZero2TwoPI.md"}]},{"text":"Other","collapsed":true,"items":[{"text":"PointCal","link":"/../../docs/math/classes/PointCal.md"},{"text":"point","link":"/../../docs/math/type-aliases/point.md"},{"text":"Point","link":"/../../docs/math/type-aliases/Point-1.md"}]}]